LICENSE
MANIFEST.in
README.md
setup.py
fyve/__init__.py
fyve/fyve.py
fyve.egg-info/PKG-INFO
fyve.egg-info/SOURCES.txt
fyve.egg-info/dependency_links.txt
fyve.egg-info/not-zip-safe
fyve.egg-info/top_level.txt