Metadata-Version: 1.0
Name: fyve
Version: 1.1.0
Summary: A library to overcomplicated five--the Python way.
Home-page: https://github.com/th13/fyve
Author: Trevor Helms
Author-email: me@trevorhelms.com
License: MIT
Platform: UNKNOWN
